pdm_manage_version-0.1.0.dist-info/METADATA
pdm_manage_version-0.1.0.dist-info/WHEEL
pdm_manage_version-0.1.0.dist-info/entry_points.txt
plugin.py
pdm_manage_version-0.1.0.dist-info/RECORD
