Metadata-Version: 2.1
Name: pdm-manage-version
Version: 0.1.0
Summary: `pdm version` working like `poetry version`
Author-Email: Marco Acierno <marcoaciernoemail@gmail.com>
License: MIT
Requires-Python: >=3.9
Requires-Dist: packaging>=23.0
